<?xml version='1.0' encoding='utf-8'?>
<annotation>
	<folder>images</folder>
	<filename>127_007_aug12_heavy_normal_motion_blur_night_time.jpg</filename>
	<path>/Users/jvarghese/Documents/TrafficSignProject/organized_dataset/Cautionary_Road_Signs/127_Staggered_Intersection/images/127_007.jpg</path>
	<source>
		<database>Unknown</database>
	</source>
	<size>
		<width>640</width>
		<height>640</height>
		<depth>3</depth>
	</size>
	<segmented>0</segmented>
	<object>
		<name>Staggered_Intersection</name>
		<pose>Unspecified</pose>
		<truncated>0</truncated>
		<difficult>0</difficult>
		<bndbox>
			<xmin>242</xmin>
			<ymin>64</ymin>
			<xmax>410</xmax>
			<ymax>246</ymax>
		</bndbox>
	</object>
</annotation>