<?xml version='1.0' encoding='utf-8'?>
<annotation>
	<folder>images</folder>
	<filename>101_002_aug1_heavy_shadow_broken_sign_normal.jpg</filename>
	<path>/Users/jvarghese/Documents/TrafficSignProject/organized_dataset/Cautionary_Road_Signs/101_Right_Hand_Curve/images/101_002.jpg</path>
	<source>
		<database>Unknown</database>
	</source>
	<size>
		<width>640</width>
		<height>640</height>
		<depth>3</depth>
	</size>
	<segmented>0</segmented>
	<object>
		<name>Right_Hand_Curve</name>
		<pose>Unspecified</pose>
		<truncated>0</truncated>
		<difficult>0</difficult>
		<bndbox>
			<xmin>231</xmin>
			<ymin>103</ymin>
			<xmax>402</xmax>
			<ymax>256</ymax>
		</bndbox>
	</object>
</annotation>