<?xml version='1.0' encoding='utf-8'?>
<annotation>
	<folder>images</folder>
	<filename>021_001_aug13_medium_broken_sign_tilt.jpg</filename>
	<path>/Users/jvarghese/Documents/TrafficSignProject/organized_dataset/Mandatory_Road_Signs/021_Compulsory_Keep_Left/images/021_001.jpg</path>
	<source>
		<database>Unknown</database>
	</source>
	<size>
		<width>640</width>
		<height>640</height>
		<depth>3</depth>
	</size>
	<segmented>0</segmented>
	<object>
		<name>Compulsory_Keep_Left</name>
		<pose>Unspecified</pose>
		<truncated>0</truncated>
		<difficult>0</difficult>
		<bndbox>
			<xmin>214</xmin>
			<ymin>209</ymin>
			<xmax>468</xmax>
			<ymax>437</ymax>
		</bndbox>
	</object>
</annotation>